keysight/systemvue/Analysis.py
keysight/systemvue/Application.py
keysight/systemvue/DataSet.py
keysight/systemvue/Design.py
keysight/systemvue/Equations.py
keysight/systemvue/Graph.py
keysight/systemvue/GraphSeries.py
keysight/systemvue/InterpOptions.py
keysight/systemvue/Param.py
keysight/systemvue/Part.py
keysight/systemvue/SlicingOptions.py
keysight/systemvue/Variable.py
keysight/systemvue/Workspace.py
keysight/systemvue/__init__.py
keysight_systemvue-2023.1.dist-info/METADATA
keysight_systemvue-2023.1.dist-info/WHEEL
keysight_systemvue-2023.1.dist-info/top_level.txt
keysight_systemvue-2023.1.dist-info/RECORD
